airflow_providers_wherobots/__init__.py
airflow_providers_wherobots/hooks/__init__.py
airflow_providers_wherobots/hooks/base.py
airflow_providers_wherobots/hooks/rest_api.py
airflow_providers_wherobots/hooks/sql.py
airflow_providers_wherobots/operators/__init__.py
airflow_providers_wherobots/operators/run.py
airflow_providers_wherobots/operators/sql.py
airflow_providers_wherobots/wherobots/__init__.py
airflow_providers_wherobots/wherobots/models.py
airflow_providers_wherobots-1.4.3.dist-info/METADATA
airflow_providers_wherobots-1.4.3.dist-info/WHEEL
airflow_providers_wherobots-1.4.3.dist-info/licenses/LICENSE
airflow_providers_wherobots-1.4.3.dist-info/RECORD
