Metadata-Version: 2.4
Name: airflow-providers-wherobots
Version: 1.4.3
Summary: Airflow extension for communicating with Wherobots Cloud
Project-URL: Homepage, https://github.com/wherobots/airflow-provider-wherobots
Project-URL: Tracker, https://github.com/wherobots/airflow-provider-wherobots
Author-email: "zongsi.zhang" <zongsi@wherobots.com>
License-File: LICENSE
Requires-Python: <3.13,>=3.9
Requires-Dist: pydantic~=2.3
Requires-Dist: wherobots-python-dbapi>=0.19.0
